colav/__init__.py
colav/extract_data.py
colav/internal_coordinates.py
colav/strain_analysis.py
colav-0.0.4.dist-info/METADATA
colav-0.0.4.dist-info/WHEEL
colav-0.0.4.dist-info/licenses/LICENSE
colav-0.0.4.dist-info/RECORD
