Metadata-Version: 2.1
Name: colav
Version: 0.0.4
Summary: Calculate protein structural representations (dihedral angles, CA pairwise distances, and strain analysis) for downstream analysis (e.g., PCA, t-SNE, or UMAP)
Project-URL: homepage, https://rs-station.github.io/colav/
Project-URL: repository, https://github.com/rs-station/colav
Author-email: Ammaar Saeed <aasaeed@college.harvard.edu>
License: MIT License
License-File: LICENSE
Classifier: Development Status :: 3 - Alpha
Classifier: License :: OSI Approved :: MIT License
Classifier: Natural Language :: English
Classifier: Operating System :: OS Independent
Classifier: Programming Language :: Python :: 3
Classifier: Typing :: Typed
Requires-Python: >=3.7
Requires-Dist: biopandas
Requires-Dist: jupyter
Requires-Dist: numpy
Requires-Dist: scipy
Provides-Extra: dev
Requires-Dist: biopandas; extra == 'dev'
Requires-Dist: black; extra == 'dev'
Requires-Dist: pandas; extra == 'dev'
Requires-Dist: pytest; extra == 'dev'
Requires-Dist: pytest-cov; extra == 'dev'
Provides-Extra: docs
Requires-Dist: myst-parser; extra == 'docs'
Requires-Dist: sphinx; extra == 'docs'
Requires-Dist: sphinx-rtd-theme; extra == 'docs'
Provides-Extra: test
Requires-Dist: biopandas; extra == 'test'
Requires-Dist: numpy; extra == 'test'
Requires-Dist: pytest-cov; extra == 'test'
Requires-Dist: pytest>=6.0; extra == 'test'
Requires-Dist: scipy; extra == 'test'
